camembert/__init__.py
camembert/bri.cpython-37m-x86_64-linux-gnu.so
camembert/version.py
camembert/cli.py
camembert/.libs/libcsamtools-072191dd.cpython-37m-x86_64-linux-gnu.so
camembert/.libs/libcfaidx-e61b2f08.cpython-37m-x86_64-linux-gnu.so
camembert/.libs/libchtslib-ba041405.cpython-37m-x86_64-linux-gnu.so
camembert/.libs/liblzma-75668d9c-c3cacbf3.so.0.0.0
camembert/.libs/libcutils-e717b21e.cpython-37m-x86_64-linux-gnu.so
camembert/.libs/libctabix-875f182a.cpython-37m-x86_64-linux-gnu.so
camembert/.libs/libcsamfile-c9826e2d.cpython-37m-x86_64-linux-gnu.so
camembert/.libs/libcbcftools-2e966c8d.cpython-37m-x86_64-linux-gnu.so
camembert/.libs/libcbcf-79b76241.cpython-37m-x86_64-linux-gnu.so
camembert/.libs/libcvcf-9367611d.cpython-37m-x86_64-linux-gnu.so
camembert/.libs/libctabixproxies-0af4f1b4.cpython-37m-x86_64-linux-gnu.so
camembert/.libs/libz-eb09ad1d-dae26ef1.so.1.2.3
camembert/.libs/libbz2-13e8c345-c392ebe1.so.1.0.4
camembert_bri-0.0.2.dist-info/RECORD
camembert_bri-0.0.2.dist-info/top_level.txt
camembert_bri-0.0.2.dist-info/METADATA
camembert_bri-0.0.2.dist-info/WHEEL
camembert_bri-0.0.2.dist-info/entry_points.txt
