Metadata-Version: 2.1
Name: camembert-bri
Version: 0.0.2
Summary: Python interface to BRI (Bam Read Index)
Home-page: https://github.com/usajusaj/camembertpy
Author: Matej Usaj
Author-email: m.usaj@utoronto.ca
License: UNKNOWN
Download-URL: https://github.com/usajusaj/camembertpy/archive/master.zip
Keywords: bri samtools htslib read index
Platform: UNKNOWN
Classifier: Development Status :: 5 - Production/Stable
Classifier: Intended Audience :: Science/Research
Classifier: Topic :: Scientific/Engineering :: Bio-Informatics
Classifier: License :: OSI Approved :: MIT License
Classifier: Programming Language :: Python :: 2
Classifier: Programming Language :: Python :: 2.7
Classifier: Programming Language :: Python :: 3
Classifier: Programming Language :: Python :: 3.5
Classifier: Programming Language :: Python :: 3.6
Classifier: Programming Language :: Python :: 3.7
Classifier: Programming Language :: Python :: 3.8
Requires-Dist: pysam
